bigmag/__init__.py
bigmag/app.py
bigmag/app_lite.py
bigmag/cli.py
bigmag/assets/favicon.ico
bigmag/assets/style.css
bigmag-1.1.0.dist-info/licenses/LICENSE
bigmag-1.1.0.dist-info/METADATA
bigmag-1.1.0.dist-info/WHEEL
bigmag-1.1.0.dist-info/entry_points.txt
bigmag-1.1.0.dist-info/top_level.txt
bigmag-1.1.0.dist-info/RECORD
