Metadata-Version: 2.4
Name: bigmag
Version: 1.1.0
Summary: BIgMAG: Board InteGrating Metagenome-Assembled Genomes - A dashboard for metagenome quality metrics and taxonomical annotation
Home-page: https://github.com/jeffe107/BIgMAG
Author: Laurent Falquet
Author-email: Jeferyd Yepes García <jeferyd.yepes@unibe.ch>
License: MIT
Project-URL: Homepage, https://github.com/jeffe107/BIgMAG
Project-URL: Repository, https://github.com/jeffe107/BIgMAG.git
Project-URL: Documentation, https://github.com/jeffe107/BIgMAG
Project-URL: Bug Tracker, https://github.com/jeffe107/BIgMAG/issues
Keywords: metagenomics,dashboard,visualization,MAG,quality-control
Classifier: Development Status :: 4 - Beta
Classifier: Intended Audience :: Science/Research
Classifier: License :: OSI Approved :: MIT License
Classifier: Programming Language :: Python :: 3
Classifier: Programming Language :: Python :: 3.8
Classifier: Programming Language :: Python :: 3.9
Classifier: Programming Language :: Python :: 3.10
Classifier: Programming Language :: Python :: 3.11
Classifier: Topic :: Scientific/Engineering :: Bio-Informatics
Requires-Python: >=3.8
License-File: LICENSE
Requires-Dist: dash==2.16.1
Requires-Dist: dash-bootstrap-components==1.5.0
Requires-Dist: dash-daq==0.5.0
Requires-Dist: numpy==1.23.5
Requires-Dist: pandas==2.0.1
Requires-Dist: plotly==5.19.0
Requires-Dist: gunicorn
Requires-Dist: dash-bio
Requires-Dist: scikit-posthocs==0.9.0
Requires-Dist: scipy==1.13.0
Requires-Dist: pingouin==0.5.4
Provides-Extra: dev
Requires-Dist: pytest>=7.0; extra == "dev"
Requires-Dist: build>=0.10.0; extra == "dev"
Requires-Dist: twine>=4.0.0; extra == "dev"
Dynamic: home-page
Dynamic: license-file
Dynamic: requires-python
